{"rect": {"x": 365.0, "y": 180.0, "width": 302.0, "height": 844.0}, "parts": {"position": {"x": 49, "y": 65}, "size": {"x": 128.0, "y": 128.0}, "images": {"000": 0, "001": 0, "002": 0, "005": 0, "006": 0, "007": 1, "008": 1, "010": 1, "011": 1, "012": 0, "013": 0, "014": 0, "015": 0, "016": 0, "017": 0, "018": 0, "020": 1, "021": 1, "022": 1, "023": 1, "024": 1, "025": 1, "026": 1, "027": 1, "028": 0, "029": 0, "030": 0, "031": 0, "032": 0, "034": 0, "035": 0, "036": 1, "037": 1, "038": 1, "042": 1, "043": 1, "046": 0, "047": 0, "048": 0, "049": 0, "050": 1, "051": 1, "052": 1, "053": 1, "054": 2, "055": 2}}}